simple-version-manager/__init__.py
simple-version-manager/simple_version_manager.py
simple-version-manager/version.py
simple-version-manager/test/__init__.py
simple-version-mananger/__init__.py
simple-version-mananger/simple_version_manager.py
simple-version-mananger/test/__init__.py
simple_version_manager/__init__.py
simple_version_manager/simple_version_manager.py
simple_version_manager/version.py
simple_version_manager/test/__init__.py
simple_version_manager-0.1.0.dist-info/DESCRIPTION.rst
simple_version_manager-0.1.0.dist-info/METADATA
simple_version_manager-0.1.0.dist-info/RECORD
simple_version_manager-0.1.0.dist-info/WHEEL
simple_version_manager-0.1.0.dist-info/entry_points.txt
simple_version_manager-0.1.0.dist-info/metadata.json
simple_version_manager-0.1.0.dist-info/top_level.txt
