Metadata-Version: 2.0
Name: simple-version-manager
Version: 0.1.0
Summary: Tool for version tag update
Home-page: https://github.com/simontorres/simple-version-manager
Author: Simon Torres
Author-email: storres@ctio.noao.edu
License: BSD-3-Clause
Keywords: version
Platform: UNKNOWN
